setup.py
eXpMPP.egg-info/PKG-INFO
eXpMPP.egg-info/SOURCES.txt
eXpMPP.egg-info/dependency_links.txt
eXpMPP.egg-info/requires.txt
eXpMPP.egg-info/top_level.txt
expmpp/__init__.py
expmpp/client.py