Metadata-Version: 1.0
Name: eXpMPP
Version: 1.0.3
Summary: XMPP notifications for psychology experiments
Home-page: https://github.com/louist87/expmpp
Author: Louis Thibault
Author-email: louist87@gmail.com
License: GPLv3.0
Keywords: experiment,psychology,XMPP,google talk
Platform: UNKNOWN
